python_example_sdk_debug/__init__.py
python_example_sdk_debug/sdk.py
python_example_sdk_debug-0.1.3.dist-info/METADATA
python_example_sdk_debug-0.1.3.dist-info/WHEEL
python_example_sdk_debug-0.1.3.dist-info/top_level.txt
python_example_sdk_debug-0.1.3.dist-info/RECORD
