Metadata-Version: 2.1
Name: python_example_sdk_debug
Version: 0.1.3
Summary: A description of random_lib_debug.
Home-page: https://github.com/yourusername/python-example-sdk
Author: Your Name
Author-email: Your Name <you@example.com>
